{
  "id": "5bd900e5fdcd4f5a99aa25ae0fc660b4",
  "price": {
    "totalPaymentPrice": {
      "paymentCurrencyAmount": 44900,
      "paymentCurrencyCode": "RUB",
      "paymentCurrencyExchangeRate": 1,
      "paymentCurrencySymbol": "₽"
    },
    "totalPrice": {
      "basePayoutCurrencyCode": "USD",
      "basePayoutPrice": 619,
      "convenienceFee": 0,
      "currencyCode": "RUB",
      "discount": 0,
      "discountPrice": 44900,
      "originalPrice": 44900,
      "originalUnitPrice": null,
      "unitPrice": null,
      "vat": 0,
      "voucherDiscount": 0
    }
  }
}