{
  "id": "1663ee9646ac45f18aebe6c2288ac877",
  "price": {
    "totalPaymentPrice": {
      "paymentCurrencyAmount": 4094,
      "paymentCurrencyCode": "SAR",
      "paymentCurrencyExchangeRate": 1,
      "paymentCurrencySymbol": "ر.س"
    },
    "totalPrice": {
      "basePayoutCurrencyCode": "USD",
      "basePayoutPrice": 949,
      "convenienceFee": 0,
      "currencyCode": "SAR",
      "discount": 2205,
      "discountPrice": 4094,
      "originalPrice": 6299,
      "originalUnitPrice": null,
      "unitPrice": null,
      "vat": 534,
      "voucherDiscount": 0
    }
  }
}