{
  "id": "ea7d6a6a70674f77b96f6bff4c0261d7",
  "price": {
    "totalPaymentPrice": {
      "paymentCurrencyAmount": 5249,
      "paymentCurrencyCode": "SAR",
      "paymentCurrencyExchangeRate": 1,
      "paymentCurrencySymbol": "ر.س"
    },
    "totalPrice": {
      "basePayoutCurrencyCode": "USD",
      "basePayoutPrice": 1217,
      "convenienceFee": 0,
      "currencyCode": "SAR",
      "discount": 12250,
      "discountPrice": 5249,
      "originalPrice": 17499,
      "originalUnitPrice": null,
      "unitPrice": null,
      "vat": 685,
      "voucherDiscount": 0
    }
  }
}