{
  "id": "0b2511694c604e1b8dc597dd096fc9c1",
  "price": {
    "totalPaymentPrice": {
      "paymentCurrencyAmount": 6700,
      "paymentCurrencyCode": "TRY",
      "paymentCurrencyExchangeRate": 1,
      "paymentCurrencySymbol": "₺"
    },
    "totalPrice": {
      "basePayoutCurrencyCode": "USD",
      "basePayoutPrice": 302,
      "convenienceFee": 0,
      "currencyCode": "TRY",
      "discount": 0,
      "discountPrice": 6700,
      "originalPrice": 6700,
      "originalUnitPrice": null,
      "unitPrice": null,
      "vat": 1022,
      "voucherDiscount": 0
    }
  }
}