{
  "id": "a67f1b86d3e64b68bdb2967e158df687",
  "price": {
    "totalPaymentPrice": {
      "paymentCurrencyAmount": 600,
      "paymentCurrencyCode": "TRY",
      "paymentCurrencyExchangeRate": 1,
      "paymentCurrencySymbol": "₺"
    },
    "totalPrice": {
      "basePayoutCurrencyCode": "USD",
      "basePayoutPrice": 28,
      "convenienceFee": 0,
      "currencyCode": "TRY",
      "discount": 200,
      "discountPrice": 600,
      "originalPrice": 800,
      "originalUnitPrice": null,
      "unitPrice": null,
      "vat": 92,
      "voucherDiscount": 0
    }
  }
}