{
  "id": "14dde2b7fd5a4fa09302a2cfaf1c3748",
  "price": {
    "totalPaymentPrice": {
      "paymentCurrencyAmount": 500,
      "paymentCurrencyCode": "CHF",
      "paymentCurrencyExchangeRate": 1,
      "paymentCurrencySymbol": "Fr."
    },
    "totalPrice": {
      "basePayoutCurrencyCode": "USD",
      "basePayoutPrice": 499,
      "convenienceFee": 0,
      "currencyCode": "CHF",
      "discount": 0,
      "discountPrice": 500,
      "originalPrice": 500,
      "originalUnitPrice": null,
      "unitPrice": null,
      "vat": 36,
      "voucherDiscount": 0
    }
  }
}