{
  "id": "d1e539716c594ae5980d5e0984d3803f",
  "price": {
    "totalPaymentPrice": {
      "paymentCurrencyAmount": 2090,
      "paymentCurrencyCode": "CHF",
      "paymentCurrencyExchangeRate": 1,
      "paymentCurrencySymbol": "Fr."
    },
    "totalPrice": {
      "basePayoutCurrencyCode": "USD",
      "basePayoutPrice": 2110,
      "convenienceFee": 0,
      "currencyCode": "CHF",
      "discount": 0,
      "discountPrice": 2090,
      "originalPrice": 2090,
      "originalUnitPrice": null,
      "unitPrice": null,
      "vat": 149,
      "voucherDiscount": 0
    }
  }
}