{
  "id": "2b6df25d595546f58275daf655932704",
  "price": {
    "totalPaymentPrice": {
      "paymentCurrencyAmount": 8424,
      "paymentCurrencyCode": "MXN",
      "paymentCurrencyExchangeRate": 1,
      "paymentCurrencySymbol": "$"
    },
    "totalPrice": {
      "basePayoutCurrencyCode": "USD",
      "basePayoutPrice": 428,
      "convenienceFee": 0,
      "currencyCode": "MXN",
      "discount": 25275,
      "discountPrice": 8424,
      "originalPrice": 33699,
      "originalUnitPrice": null,
      "unitPrice": null,
      "vat": 0,
      "voucherDiscount": 0
    }
  }
}