{
  "id": "3443dbe85c43483f8205fdff619c4286",
  "price": {
    "totalPaymentPrice": {
      "paymentCurrencyAmount": 9990,
      "paymentCurrencyCode": "DKK",
      "paymentCurrencyExchangeRate": 1,
      "paymentCurrencySymbol": "kr."
    },
    "totalPrice": {
      "basePayoutCurrencyCode": "USD",
      "basePayoutPrice": 1173,
      "convenienceFee": 0,
      "currencyCode": "DKK",
      "discount": 0,
      "discountPrice": 9990,
      "originalPrice": 9990,
      "originalUnitPrice": null,
      "unitPrice": null,
      "vat": 1998,
      "voucherDiscount": 0
    }
  }
}