{
  "id": "0b9cf9fcc3b142e3a0262e67c440de3b",
  "price": {
    "totalPaymentPrice": {
      "paymentCurrencyAmount": 2699900,
      "paymentCurrencyCode": "IDR",
      "paymentCurrencyExchangeRate": 1,
      "paymentCurrencySymbol": "Rp"
    },
    "totalPrice": {
      "basePayoutCurrencyCode": "USD",
      "basePayoutPrice": 161,
      "convenienceFee": 0,
      "currencyCode": "IDR",
      "discount": 8100000,
      "discountPrice": 2699900,
      "originalPrice": 10799900,
      "originalUnitPrice": null,
      "unitPrice": null,
      "vat": 267558,
      "voucherDiscount": 0
    }
  }
}