{
  "id": "1d309546149d4646a24b15b28eedb358",
  "price": {
    "totalPaymentPrice": {
      "paymentCurrencyAmount": 13839900,
      "paymentCurrencyCode": "IDR",
      "paymentCurrencyExchangeRate": 1,
      "paymentCurrencySymbol": "Rp"
    },
    "totalPrice": {
      "basePayoutCurrencyCode": "USD",
      "basePayoutPrice": 829,
      "convenienceFee": 0,
      "currencyCode": "IDR",
      "discount": 3460000,
      "discountPrice": 13839900,
      "originalPrice": 17299900,
      "originalUnitPrice": null,
      "unitPrice": null,
      "vat": 1371522,
      "voucherDiscount": 0
    }
  }
}