{
  "id": "41ece6a7d9b847babbfe9c064f94f622",
  "price": {
    "totalPaymentPrice": {
      "paymentCurrencyAmount": 13999900,
      "paymentCurrencyCode": "IDR",
      "paymentCurrencyExchangeRate": 1,
      "paymentCurrencySymbol": "Rp"
    },
    "totalPrice": {
      "basePayoutCurrencyCode": "USD",
      "basePayoutPrice": 803,
      "convenienceFee": 0,
      "currencyCode": "IDR",
      "discount": 0,
      "discountPrice": 13999900,
      "originalPrice": 13999900,
      "originalUnitPrice": null,
      "unitPrice": null,
      "vat": 1387377,
      "voucherDiscount": 0
    }
  }
}