{
  "id": "48f9d1259f304e97890a1211c563d314",
  "price": {
    "totalPaymentPrice": {
      "paymentCurrencyAmount": 118999500,
      "paymentCurrencyCode": "IDR",
      "paymentCurrencyExchangeRate": 1,
      "paymentCurrencySymbol": "Rp"
    },
    "totalPrice": {
      "basePayoutCurrencyCode": "USD",
      "basePayoutPrice": 7176,
      "convenienceFee": 0,
      "currencyCode": "IDR",
      "discount": 0,
      "discountPrice": 118999500,
      "originalPrice": 118999500,
      "originalUnitPrice": null,
      "unitPrice": null,
      "vat": 11792743,
      "voucherDiscount": 0
    }
  }
}