{
  "id": "bd43f9cf36c148df8026a6e43f72f0d5",
  "price": {
    "totalPaymentPrice": {
      "paymentCurrencyAmount": 1450000,
      "paymentCurrencyCode": "IDR",
      "paymentCurrencyExchangeRate": 1,
      "paymentCurrencySymbol": "Rp"
    },
    "totalPrice": {
      "basePayoutCurrencyCode": "USD",
      "basePayoutPrice": 88,
      "convenienceFee": 0,
      "currencyCode": "IDR",
      "discount": 1450000,
      "discountPrice": 1450000,
      "originalPrice": 2900000,
      "originalUnitPrice": null,
      "unitPrice": null,
      "vat": 143694,
      "voucherDiscount": 0
    }
  }
}