{
  "id": "c0f09d4ca9c1491fa58528decef4bfeb",
  "price": {
    "totalPaymentPrice": {
      "paymentCurrencyAmount": 2219900,
      "paymentCurrencyCode": "IDR",
      "paymentCurrencyExchangeRate": 1,
      "paymentCurrencySymbol": "Rp"
    },
    "totalPrice": {
      "basePayoutCurrencyCode": "USD",
      "basePayoutPrice": 129,
      "convenienceFee": 0,
      "currencyCode": "IDR",
      "discount": 3780000,
      "discountPrice": 2219900,
      "originalPrice": 5999900,
      "originalUnitPrice": null,
      "unitPrice": null,
      "vat": 219990,
      "voucherDiscount": 0
    }
  }
}