{
  "id": "e7c2a45dc8334570bee612abeb60a654",
  "price": {
    "totalPaymentPrice": {
      "paymentCurrencyAmount": 24599900,
      "paymentCurrencyCode": "IDR",
      "paymentCurrencyExchangeRate": 1,
      "paymentCurrencySymbol": "Rp"
    },
    "totalPrice": {
      "basePayoutCurrencyCode": "USD",
      "basePayoutPrice": 1419,
      "convenienceFee": 0,
      "currencyCode": "IDR",
      "discount": 0,
      "discountPrice": 24599900,
      "originalPrice": 24599900,
      "originalUnitPrice": null,
      "unitPrice": null,
      "vat": 2437828,
      "voucherDiscount": 0
    }
  }
}