{
  "id": "e9b4e035ec4346c59328a854b4bba7fe",
  "price": {
    "totalPaymentPrice": {
      "paymentCurrencyAmount": 25110000,
      "paymentCurrencyCode": "IDR",
      "paymentCurrencyExchangeRate": 1,
      "paymentCurrencySymbol": "Rp"
    },
    "totalPrice": {
      "basePayoutCurrencyCode": "USD",
      "basePayoutPrice": 1476,
      "convenienceFee": 0,
      "currencyCode": "IDR",
      "discount": 2790000,
      "discountPrice": 25110000,
      "originalPrice": 27900000,
      "originalUnitPrice": null,
      "unitPrice": null,
      "vat": 2488378,
      "voucherDiscount": 0
    }
  }
}