{
  "id": "fb557dcb1bfe4a5791b3a11a83f52e90",
  "price": {
    "totalPaymentPrice": {
      "paymentCurrencyAmount": 1566000,
      "paymentCurrencyCode": "IDR",
      "paymentCurrencyExchangeRate": 1,
      "paymentCurrencySymbol": "Rp"
    },
    "totalPrice": {
      "basePayoutCurrencyCode": "USD",
      "basePayoutPrice": 91,
      "convenienceFee": 0,
      "currencyCode": "IDR",
      "discount": 4234000,
      "discountPrice": 1566000,
      "originalPrice": 5800000,
      "originalUnitPrice": null,
      "unitPrice": null,
      "vat": 155189,
      "voucherDiscount": 0
    }
  }
}