{
  "id": "1e2dec7f41314405bac12eb74c20254f",
  "price": {
    "totalPaymentPrice": {
      "paymentCurrencyAmount": 3297,
      "paymentCurrencyCode": "ILS",
      "paymentCurrencyExchangeRate": 1,
      "paymentCurrencySymbol": "₪"
    },
    "totalPrice": {
      "basePayoutCurrencyCode": "USD",
      "basePayoutPrice": 935,
      "convenienceFee": 0,
      "currencyCode": "ILS",
      "discount": 3298,
      "discountPrice": 3297,
      "originalPrice": 6595,
      "originalUnitPrice": null,
      "unitPrice": null,
      "vat": 0,
      "voucherDiscount": 0
    }
  }
}