{
  "id": "3299949f391a4dbb9e0c4b28b683992c",
  "price": {
    "totalPaymentPrice": {
      "paymentCurrencyAmount": 3737,
      "paymentCurrencyCode": "ILS",
      "paymentCurrencyExchangeRate": 1,
      "paymentCurrencySymbol": "₪"
    },
    "totalPrice": {
      "basePayoutCurrencyCode": "USD",
      "basePayoutPrice": 1070,
      "convenienceFee": 0,
      "currencyCode": "ILS",
      "discount": 3058,
      "discountPrice": 3737,
      "originalPrice": 6795,
      "originalUnitPrice": null,
      "unitPrice": null,
      "vat": 0,
      "voucherDiscount": 0
    }
  }
}