{
  "id": "15a07ae229db4628937c0e159f8f2928",
  "price": {
    "totalPaymentPrice": {
      "paymentCurrencyAmount": 44900,
      "paymentCurrencyCode": "INR",
      "paymentCurrencyExchangeRate": 1,
      "paymentCurrencySymbol": "₹"
    },
    "totalPrice": {
      "basePayoutCurrencyCode": "USD",
      "basePayoutPrice": 462,
      "convenienceFee": 0,
      "currencyCode": "INR",
      "discount": 0,
      "discountPrice": 44900,
      "originalPrice": 44900,
      "originalUnitPrice": null,
      "unitPrice": null,
      "vat": 6849,
      "voucherDiscount": 0
    }
  }
}