{
  "id": "48705e2229b34bd4b224725f2376d6b1",
  "price": {
    "totalPaymentPrice": {
      "paymentCurrencyAmount": 5700,
      "paymentCurrencyCode": "INR",
      "paymentCurrencyExchangeRate": 1,
      "paymentCurrencySymbol": "₹"
    },
    "totalPrice": {
      "basePayoutCurrencyCode": "USD",
      "basePayoutPrice": 59,
      "convenienceFee": 0,
      "currencyCode": "INR",
      "discount": 13300,
      "discountPrice": 5700,
      "originalPrice": 19000,
      "originalUnitPrice": null,
      "unitPrice": null,
      "vat": 869,
      "voucherDiscount": 0
    }
  }
}