{
  "id": "5b51238feca048ecb426351859ea3014",
  "price": {
    "totalPaymentPrice": {
      "paymentCurrencyAmount": 70587,
      "paymentCurrencyCode": "INR",
      "paymentCurrencyExchangeRate": 1,
      "paymentCurrencySymbol": "₹"
    },
    "totalPrice": {
      "basePayoutCurrencyCode": "USD",
      "basePayoutPrice": 724,
      "convenienceFee": 0,
      "currencyCode": "INR",
      "discount": 70587,
      "discountPrice": 70587,
      "originalPrice": 141174,
      "originalUnitPrice": null,
      "unitPrice": null,
      "vat": 10768,
      "voucherDiscount": 0
    }
  }
}