{
  "id": "665393ab4aca4ce4a2cf8fba6c5372ce",
  "price": {
    "totalPaymentPrice": {
      "paymentCurrencyAmount": 74850,
      "paymentCurrencyCode": "INR",
      "paymentCurrencyExchangeRate": 1,
      "paymentCurrencySymbol": "₹"
    },
    "totalPrice": {
      "basePayoutCurrencyCode": "USD",
      "basePayoutPrice": 771,
      "convenienceFee": 0,
      "currencyCode": "INR",
      "discount": 74851,
      "discountPrice": 74850,
      "originalPrice": 149701,
      "originalUnitPrice": null,
      "unitPrice": null,
      "vat": 11418,
      "voucherDiscount": 0
    }
  }
}