{
  "id": "a141915f0de3494791151b205a712cda",
  "price": {
    "totalPaymentPrice": {
      "paymentCurrencyAmount": 17675,
      "paymentCurrencyCode": "INR",
      "paymentCurrencyExchangeRate": 1,
      "paymentCurrencySymbol": "₹"
    },
    "totalPrice": {
      "basePayoutCurrencyCode": "USD",
      "basePayoutPrice": 183,
      "convenienceFee": 0,
      "currencyCode": "INR",
      "discount": 53025,
      "discountPrice": 17675,
      "originalPrice": 70700,
      "originalUnitPrice": null,
      "unitPrice": null,
      "vat": 2696,
      "voucherDiscount": 0
    }
  }
}