{
  "id": "a2ec46a5ebb94da382196ed88624cefc",
  "price": {
    "totalPaymentPrice": {
      "paymentCurrencyAmount": 23900,
      "paymentCurrencyCode": "INR",
      "paymentCurrencyExchangeRate": 1,
      "paymentCurrencySymbol": "₹"
    },
    "totalPrice": {
      "basePayoutCurrencyCode": "USD",
      "basePayoutPrice": 272,
      "convenienceFee": 0,
      "currencyCode": "INR",
      "discount": 0,
      "discountPrice": 23900,
      "originalPrice": 23900,
      "originalUnitPrice": null,
      "unitPrice": null,
      "vat": 3646,
      "voucherDiscount": 0
    }
  }
}