{
  "id": "bfcc9b82edbd4c828dabc1c2959f657d",
  "price": {
    "totalPaymentPrice": {
      "paymentCurrencyAmount": 20940,
      "paymentCurrencyCode": "INR",
      "paymentCurrencyExchangeRate": 1,
      "paymentCurrencySymbol": "₹"
    },
    "totalPrice": {
      "basePayoutCurrencyCode": "USD",
      "basePayoutPrice": 216,
      "convenienceFee": 0,
      "currencyCode": "INR",
      "discount": 13960,
      "discountPrice": 20940,
      "originalPrice": 34900,
      "originalUnitPrice": null,
      "unitPrice": null,
      "vat": 3194,
      "voucherDiscount": 0
    }
  }
}