{
  "id": "d0c5fbc1adf847e9b67ae5c9df039320",
  "price": {
    "totalPaymentPrice": {
      "paymentCurrencyAmount": 99270,
      "paymentCurrencyCode": "INR",
      "paymentCurrencyExchangeRate": 1,
      "paymentCurrencySymbol": "₹"
    },
    "totalPrice": {
      "basePayoutCurrencyCode": "USD",
      "basePayoutPrice": 1024,
      "convenienceFee": 0,
      "currencyCode": "INR",
      "discount": 0,
      "discountPrice": 99270,
      "originalPrice": 99270,
      "originalUnitPrice": null,
      "unitPrice": null,
      "vat": 15143,
      "voucherDiscount": 0
    }
  }
}