{
  "id": "da763a33956745888bea060de7ecf059",
  "price": {
    "totalPaymentPrice": {
      "paymentCurrencyAmount": 32725,
      "paymentCurrencyCode": "INR",
      "paymentCurrencyExchangeRate": 1,
      "paymentCurrencySymbol": "₹"
    },
    "totalPrice": {
      "basePayoutCurrencyCode": "USD",
      "basePayoutPrice": 337,
      "convenienceFee": 0,
      "currencyCode": "INR",
      "discount": 26775,
      "discountPrice": 32725,
      "originalPrice": 59500,
      "originalUnitPrice": null,
      "unitPrice": null,
      "vat": 4992,
      "voucherDiscount": 0
    }
  }
}