{
  "id": "1e3f4a2eb99241a0aeb9eae125b8cfde",
  "price": {
    "totalPaymentPrice": {
      "paymentCurrencyAmount": 19500,
      "paymentCurrencyCode": "CNY",
      "paymentCurrencyExchangeRate": 1,
      "paymentCurrencySymbol": "¥"
    },
    "totalPrice": {
      "basePayoutCurrencyCode": "USD",
      "basePayoutPrice": 2826,
      "convenienceFee": 0,
      "currencyCode": "CNY",
      "discount": 45500,
      "discountPrice": 19500,
      "originalPrice": 65000,
      "originalUnitPrice": null,
      "unitPrice": null,
      "vat": 0,
      "voucherDiscount": 0
    }
  }
}