{
  "id": "211979befb864422891b15f2019b938b",
  "price": {
    "totalPaymentPrice": {
      "paymentCurrencyAmount": 11800,
      "paymentCurrencyCode": "CNY",
      "paymentCurrencyExchangeRate": 1,
      "paymentCurrencySymbol": "¥"
    },
    "totalPrice": {
      "basePayoutCurrencyCode": "USD",
      "basePayoutPrice": 1623,
      "convenienceFee": 0,
      "currencyCode": "CNY",
      "discount": 0,
      "discountPrice": 11800,
      "originalPrice": 11800,
      "originalUnitPrice": null,
      "unitPrice": null,
      "vat": 0,
      "voucherDiscount": 0
    }
  }
}