{
  "id": "7c66206886de4ea88ae81022deaa13eb",
  "price": {
    "totalPaymentPrice": {
      "paymentCurrencyAmount": 1206,
      "paymentCurrencyCode": "CNY",
      "paymentCurrencyExchangeRate": 1,
      "paymentCurrencySymbol": "¥"
    },
    "totalPrice": {
      "basePayoutCurrencyCode": "USD",
      "basePayoutPrice": 175,
      "convenienceFee": 0,
      "currencyCode": "CNY",
      "discount": 594,
      "discountPrice": 1206,
      "originalPrice": 1800,
      "originalUnitPrice": null,
      "unitPrice": null,
      "vat": 0,
      "voucherDiscount": 0
    }
  }
}