{
  "id": "e81c7c5a1b4545b4b35ac49a66849505",
  "price": {
    "totalPaymentPrice": {
      "paymentCurrencyAmount": 32900,
      "paymentCurrencyCode": "CNY",
      "paymentCurrencyExchangeRate": 1,
      "paymentCurrencySymbol": "¥"
    },
    "totalPrice": {
      "basePayoutCurrencyCode": "USD",
      "basePayoutPrice": 4769,
      "convenienceFee": 0,
      "currencyCode": "CNY",
      "discount": 0,
      "discountPrice": 32900,
      "originalPrice": 32900,
      "originalUnitPrice": null,
      "unitPrice": null,
      "vat": 0,
      "voucherDiscount": 0
    }
  }
}