{
  "id": "40a96ee1c902442085394b4e70a0ba22",
  "price": {
    "totalPaymentPrice": {
      "paymentCurrencyAmount": 32000,
      "paymentCurrencyCode": "AED",
      "paymentCurrencyExchangeRate": 1,
      "paymentCurrencySymbol": "د.إ"
    },
    "totalPrice": {
      "basePayoutCurrencyCode": "USD",
      "basePayoutPrice": 8713,
      "convenienceFee": 0,
      "currencyCode": "AED",
      "discount": 0,
      "discountPrice": 32000,
      "originalPrice": 32000,
      "originalUnitPrice": null,
      "unitPrice": null,
      "vat": 0,
      "voucherDiscount": 0
    }
  }
}