{
  "id": "fd62ac6192444a10947dc9372b7a0653",
  "price": {
    "totalPaymentPrice": {
      "paymentCurrencyAmount": 450,
      "paymentCurrencyCode": "AED",
      "paymentCurrencyExchangeRate": 1,
      "paymentCurrencySymbol": "د.إ"
    },
    "totalPrice": {
      "basePayoutCurrencyCode": "USD",
      "basePayoutPrice": 123,
      "convenienceFee": 0,
      "currencyCode": "AED",
      "discount": 450,
      "discountPrice": 450,
      "originalPrice": 900,
      "originalUnitPrice": null,
      "unitPrice": null,
      "vat": 0,
      "voucherDiscount": 0
    }
  }
}