{
  "id": "ee4a0ce941fa47049e5957d9c9d63a63",
  "price": {
    "totalPaymentPrice": {
      "paymentCurrencyAmount": 419,
      "paymentCurrencyCode": "USD",
      "paymentCurrencyExchangeRate": 1,
      "paymentCurrencySymbol": "$"
    },
    "totalPrice": {
      "basePayoutCurrencyCode": "USD",
      "basePayoutPrice": 419,
      "convenienceFee": 0,
      "currencyCode": "USD",
      "discount": 180,
      "discountPrice": 419,
      "originalPrice": 599,
      "originalUnitPrice": null,
      "unitPrice": null,
      "vat": 0,
      "voucherDiscount": 0
    }
  }
}