{
  "id": "72a4018ec314412ebf3740c612aa69c1",
  "price": {
    "totalPaymentPrice": {
      "paymentCurrencyAmount": 1350,
      "paymentCurrencyCode": "PLN",
      "paymentCurrencyExchangeRate": 1,
      "paymentCurrencySymbol": "zł"
    },
    "totalPrice": {
      "basePayoutCurrencyCode": "USD",
      "basePayoutPrice": 248,
      "convenienceFee": 0,
      "currencyCode": "PLN",
      "discount": 0,
      "discountPrice": 1350,
      "originalPrice": 1350,
      "originalUnitPrice": null,
      "unitPrice": null,
      "vat": 252,
      "voucherDiscount": 0
    }
  }
}