{
  "id": "8e53c876bb7f48b88edfb7b904e72d82",
  "price": {
    "totalPaymentPrice": {
      "paymentCurrencyAmount": 12499,
      "paymentCurrencyCode": "PLN",
      "paymentCurrencyExchangeRate": 1,
      "paymentCurrencySymbol": "zł"
    },
    "totalPrice": {
      "basePayoutCurrencyCode": "USD",
      "basePayoutPrice": 2031,
      "convenienceFee": 0,
      "currencyCode": "PLN",
      "discount": 0,
      "discountPrice": 12499,
      "originalPrice": 12499,
      "originalUnitPrice": null,
      "unitPrice": null,
      "vat": 2337,
      "voucherDiscount": 0
    }
  }
}