{
  "id": "985b0d111a644835acaf7a12118e21c0",
  "price": {
    "totalPaymentPrice": {
      "paymentCurrencyAmount": 432,
      "paymentCurrencyCode": "PLN",
      "paymentCurrencyExchangeRate": 1,
      "paymentCurrencySymbol": "zł"
    },
    "totalPrice": {
      "basePayoutCurrencyCode": "USD",
      "basePayoutPrice": 81,
      "convenienceFee": 0,
      "currencyCode": "PLN",
      "discount": 0,
      "discountPrice": 432,
      "originalPrice": 432,
      "originalUnitPrice": null,
      "unitPrice": null,
      "vat": 81,
      "voucherDiscount": 0
    }
  }
}