{
  "id": "d8aa3bccd0b142dd8236bbda1f0930c6",
  "price": {
    "totalPaymentPrice": {
      "paymentCurrencyAmount": 1725,
      "paymentCurrencyCode": "PLN",
      "paymentCurrencyExchangeRate": 1,
      "paymentCurrencySymbol": "zł"
    },
    "totalPrice": {
      "basePayoutCurrencyCode": "USD",
      "basePayoutPrice": 326,
      "convenienceFee": 0,
      "currencyCode": "PLN",
      "discount": 5175,
      "discountPrice": 1725,
      "originalPrice": 6900,
      "originalUnitPrice": null,
      "unitPrice": null,
      "vat": 323,
      "voucherDiscount": 0
    }
  }
}