{
  "id": "328a1ddfed7e4839bbb6e4c2b0b5ac9d",
  "price": {
    "totalPaymentPrice": {
      "paymentCurrencyAmount": 850,
      "paymentCurrencyCode": "AUD",
      "paymentCurrencyExchangeRate": 1,
      "paymentCurrencySymbol": "$"
    },
    "totalPrice": {
      "basePayoutCurrencyCode": "USD",
      "basePayoutPrice": 486,
      "convenienceFee": 0,
      "currencyCode": "AUD",
      "discount": 0,
      "discountPrice": 850,
      "originalPrice": 850,
      "originalUnitPrice": null,
      "unitPrice": null,
      "vat": 77,
      "voucherDiscount": 0
    }
  }
}