{
  "id": "84ce9926a2d04c06b9b8e99ae09d964c",
  "price": {
    "totalPaymentPrice": {
      "paymentCurrencyAmount": 7295,
      "paymentCurrencyCode": "AUD",
      "paymentCurrencyExchangeRate": 1,
      "paymentCurrencySymbol": "$"
    },
    "totalPrice": {
      "basePayoutCurrencyCode": "USD",
      "basePayoutPrice": 4453,
      "convenienceFee": 0,
      "currencyCode": "AUD",
      "discount": 0,
      "discountPrice": 7295,
      "originalPrice": 7295,
      "originalUnitPrice": null,
      "unitPrice": null,
      "vat": 663,
      "voucherDiscount": 0
    }
  }
}