{
  "id": "8ca981c6ba184fefae5e092f2c770d56",
  "price": {
    "totalPaymentPrice": {
      "paymentCurrencyAmount": 6597,
      "paymentCurrencyCode": "AUD",
      "paymentCurrencyExchangeRate": 1,
      "paymentCurrencySymbol": "$"
    },
    "totalPrice": {
      "basePayoutCurrencyCode": "USD",
      "basePayoutPrice": 4085,
      "convenienceFee": 0,
      "currencyCode": "AUD",
      "discount": 4399,
      "discountPrice": 6597,
      "originalPrice": 10996,
      "originalUnitPrice": null,
      "unitPrice": null,
      "vat": 600,
      "voucherDiscount": 0
    }
  }
}