{
  "id": "abfe7939d64f4f4d99328dc9e5096778",
  "price": {
    "totalPaymentPrice": {
      "paymentCurrencyAmount": 4556,
      "paymentCurrencyCode": "AUD",
      "paymentCurrencyExchangeRate": 1,
      "paymentCurrencySymbol": "$"
    },
    "totalPrice": {
      "basePayoutCurrencyCode": "USD",
      "basePayoutPrice": 2694,
      "convenienceFee": 0,
      "currencyCode": "AUD",
      "discount": 1139,
      "discountPrice": 4556,
      "originalPrice": 5695,
      "originalUnitPrice": null,
      "unitPrice": null,
      "vat": 414,
      "voucherDiscount": 0
    }
  }
}