{
  "id": "be9e54060e494fefb39904e63f8078b1",
  "price": {
    "totalPaymentPrice": {
      "paymentCurrencyAmount": 2150,
      "paymentCurrencyCode": "AUD",
      "paymentCurrencyExchangeRate": 1,
      "paymentCurrencySymbol": "$"
    },
    "totalPrice": {
      "basePayoutCurrencyCode": "USD",
      "basePayoutPrice": 1392,
      "convenienceFee": 0,
      "currencyCode": "AUD",
      "discount": 0,
      "discountPrice": 2150,
      "originalPrice": 2150,
      "originalUnitPrice": null,
      "unitPrice": null,
      "vat": 195,
      "voucherDiscount": 0
    }
  }
}