{
  "id": "07c9c9abde9b4713bde4f44de51b9902",
  "price": {
    "totalPaymentPrice": {
      "paymentCurrencyAmount": 5963,
      "paymentCurrencyCode": "BRL",
      "paymentCurrencyExchangeRate": 1,
      "paymentCurrencySymbol": "R$"
    },
    "totalPrice": {
      "basePayoutCurrencyCode": "USD",
      "basePayoutPrice": 1127,
      "convenienceFee": 0,
      "currencyCode": "BRL",
      "discount": 2937,
      "discountPrice": 5963,
      "originalPrice": 8900,
      "originalUnitPrice": null,
      "unitPrice": null,
      "vat": 0,
      "voucherDiscount": 0
    }
  }
}