{
  "id": "112d4a6bbc254c7fb58ca5597e40f093",
  "price": {
    "totalPaymentPrice": {
      "paymentCurrencyAmount": 13750,
      "paymentCurrencyCode": "CZK",
      "paymentCurrencyExchangeRate": 1,
      "paymentCurrencySymbol": "Kč"
    },
    "totalPrice": {
      "basePayoutCurrencyCode": "USD",
      "basePayoutPrice": 522,
      "convenienceFee": 0,
      "currencyCode": "CZK",
      "discount": 41250,
      "discountPrice": 13750,
      "originalPrice": 55000,
      "originalUnitPrice": null,
      "unitPrice": null,
      "vat": 2386,
      "voucherDiscount": 0
    }
  }
}