{
  "id": "2784e488321f4f408f278a2d262f1c69",
  "price": {
    "totalPaymentPrice": {
      "paymentCurrencyAmount": 15750,
      "paymentCurrencyCode": "CZK",
      "paymentCurrencyExchangeRate": 1,
      "paymentCurrencySymbol": "Kč"
    },
    "totalPrice": {
      "basePayoutCurrencyCode": "USD",
      "basePayoutPrice": 572,
      "convenienceFee": 0,
      "currencyCode": "CZK",
      "discount": 5250,
      "discountPrice": 15750,
      "originalPrice": 21000,
      "originalUnitPrice": null,
      "unitPrice": null,
      "vat": 2733,
      "voucherDiscount": 0
    }
  }
}