{
  "id": "3fc5e1b7ecc94fecb3a1c0f3c6ca3243",
  "price": {
    "totalPaymentPrice": {
      "paymentCurrencyAmount": 3600,
      "paymentCurrencyCode": "CZK",
      "paymentCurrencyExchangeRate": 1,
      "paymentCurrencySymbol": "Kč"
    },
    "totalPrice": {
      "basePayoutCurrencyCode": "USD",
      "basePayoutPrice": 127,
      "convenienceFee": 0,
      "currencyCode": "CZK",
      "discount": 14400,
      "discountPrice": 3600,
      "originalPrice": 18000,
      "originalUnitPrice": null,
      "unitPrice": null,
      "vat": 625,
      "voucherDiscount": 0
    }
  }
}