{
  "id": "6d6c6dcde1a647b8964bda540dfccb8c",
  "price": {
    "totalPaymentPrice": {
      "paymentCurrencyAmount": 67000,
      "paymentCurrencyCode": "CZK",
      "paymentCurrencyExchangeRate": 1,
      "paymentCurrencySymbol": "Kč"
    },
    "totalPrice": {
      "basePayoutCurrencyCode": "USD",
      "basePayoutPrice": 2480,
      "convenienceFee": 0,
      "currencyCode": "CZK",
      "discount": 0,
      "discountPrice": 67000,
      "originalPrice": 67000,
      "originalUnitPrice": null,
      "unitPrice": null,
      "vat": 11628,
      "voucherDiscount": 0
    }
  }
}