{
  "id": "c769b694ac7c4ba2b37f58cfba715a31",
  "price": {
    "totalPaymentPrice": {
      "paymentCurrencyAmount": 79950,
      "paymentCurrencyCode": "CZK",
      "paymentCurrencyExchangeRate": 1,
      "paymentCurrencySymbol": "Kč"
    },
    "totalPrice": {
      "basePayoutCurrencyCode": "USD",
      "basePayoutPrice": 2889,
      "convenienceFee": 0,
      "currencyCode": "CZK",
      "discount": 79950,
      "discountPrice": 79950,
      "originalPrice": 159900,
      "originalUnitPrice": null,
      "unitPrice": null,
      "vat": 13876,
      "voucherDiscount": 0
    }
  }
}