{
  "id": "d65d6c5c2fd54c8a9483386f08ba6955",
  "price": {
    "totalPaymentPrice": {
      "paymentCurrencyAmount": 1600,
      "paymentCurrencyCode": "CZK",
      "paymentCurrencyExchangeRate": 1,
      "paymentCurrencySymbol": "Kč"
    },
    "totalPrice": {
      "basePayoutCurrencyCode": "USD",
      "basePayoutPrice": 56,
      "convenienceFee": 0,
      "currencyCode": "CZK",
      "discount": 400,
      "discountPrice": 1600,
      "originalPrice": 2000,
      "originalUnitPrice": null,
      "unitPrice": null,
      "vat": 278,
      "voucherDiscount": 0
    }
  }
}