{
  "id": "fcd09613dbf84f04a2cf080f452dab6b",
  "price": {
    "totalPaymentPrice": {
      "paymentCurrencyAmount": 5975,
      "paymentCurrencyCode": "CZK",
      "paymentCurrencyExchangeRate": 1,
      "paymentCurrencySymbol": "Kč"
    },
    "totalPrice": {
      "basePayoutCurrencyCode": "USD",
      "basePayoutPrice": 227,
      "convenienceFee": 0,
      "currencyCode": "CZK",
      "discount": 11099,
      "discountPrice": 5975,
      "originalPrice": 17074,
      "originalUnitPrice": null,
      "unitPrice": null,
      "vat": 1037,
      "voucherDiscount": 0
    }
  }
}