{
  "id": "8dca7a113fde426b943813763d9bff4d",
  "price": {
    "totalPaymentPrice": {
      "paymentCurrencyAmount": 6496,
      "paymentCurrencyCode": "NOK",
      "paymentCurrencyExchangeRate": 1,
      "paymentCurrencySymbol": "kr"
    },
    "totalPrice": {
      "basePayoutCurrencyCode": "USD",
      "basePayoutPrice": 491,
      "convenienceFee": 0,
      "currencyCode": "NOK",
      "discount": 0,
      "discountPrice": 6496,
      "originalPrice": 6496,
      "originalUnitPrice": null,
      "unitPrice": null,
      "vat": 1299,
      "voucherDiscount": 0
    }
  }
}