{
  "id": "9931b92fef454630af387e5f90f8de2d",
  "price": {
    "totalPaymentPrice": {
      "paymentCurrencyAmount": 47940,
      "paymentCurrencyCode": "NOK",
      "paymentCurrencyExchangeRate": 1,
      "paymentCurrencySymbol": "kr"
    },
    "totalPrice": {
      "basePayoutCurrencyCode": "USD",
      "basePayoutPrice": 3919,
      "convenienceFee": 0,
      "currencyCode": "NOK",
      "discount": 31960,
      "discountPrice": 47940,
      "originalPrice": 79900,
      "originalUnitPrice": null,
      "unitPrice": null,
      "vat": 9588,
      "voucherDiscount": 0
    }
  }
}