{
  "id": "eef7b046db77484c964e1ba5b55db9bc",
  "price": {
    "totalPaymentPrice": {
      "paymentCurrencyAmount": 26910,
      "paymentCurrencyCode": "NOK",
      "paymentCurrencyExchangeRate": 1,
      "paymentCurrencySymbol": "kr"
    },
    "totalPrice": {
      "basePayoutCurrencyCode": "USD",
      "basePayoutPrice": 2105,
      "convenienceFee": 0,
      "currencyCode": "NOK",
      "discount": 26910,
      "discountPrice": 26910,
      "originalPrice": 53820,
      "originalUnitPrice": null,
      "unitPrice": null,
      "vat": 5382,
      "voucherDiscount": 0
    }
  }
}