{
  "id": "3d482183d370402584d92b22f2b5e755",
  "price": {
    "totalPaymentPrice": {
      "paymentCurrencyAmount": 3500,
      "paymentCurrencyCode": "SEK",
      "paymentCurrencyExchangeRate": 1,
      "paymentCurrencySymbol": "kr"
    },
    "totalPrice": {
      "basePayoutCurrencyCode": "USD",
      "basePayoutPrice": 278,
      "convenienceFee": 0,
      "currencyCode": "SEK",
      "discount": 0,
      "discountPrice": 3500,
      "originalPrice": 3500,
      "originalUnitPrice": null,
      "unitPrice": null,
      "vat": 700,
      "voucherDiscount": 0
    }
  }
}