{
  "id": "5c319e7b8cbf4ddb89a57e2bb5e07df5",
  "price": {
    "totalPaymentPrice": {
      "paymentCurrencyAmount": 13600,
      "paymentCurrencyCode": "SEK",
      "paymentCurrencyExchangeRate": 1,
      "paymentCurrencySymbol": "kr"
    },
    "totalPrice": {
      "basePayoutCurrencyCode": "USD",
      "basePayoutPrice": 1009,
      "convenienceFee": 0,
      "currencyCode": "SEK",
      "discount": 0,
      "discountPrice": 13600,
      "originalPrice": 13600,
      "originalUnitPrice": null,
      "unitPrice": null,
      "vat": 2720,
      "voucherDiscount": 0
    }
  }
}