{
  "id": "5f465bd399244e06965609a00dc303eb",
  "price": {
    "totalPaymentPrice": {
      "paymentCurrencyAmount": 3500,
      "paymentCurrencyCode": "SEK",
      "paymentCurrencyExchangeRate": 1,
      "paymentCurrencySymbol": "kr"
    },
    "totalPrice": {
      "basePayoutCurrencyCode": "USD",
      "basePayoutPrice": 256,
      "convenienceFee": 0,
      "currencyCode": "SEK",
      "discount": 0,
      "discountPrice": 3500,
      "originalPrice": 3500,
      "originalUnitPrice": null,
      "unitPrice": null,
      "vat": 700,
      "voucherDiscount": 0
    }
  }
}