{
  "id": "75f58e99777c46b8ab7088e001c02ff7",
  "price": {
    "totalPaymentPrice": {
      "paymentCurrencyAmount": 10720,
      "paymentCurrencyCode": "SEK",
      "paymentCurrencyExchangeRate": 1,
      "paymentCurrencySymbol": "kr"
    },
    "totalPrice": {
      "basePayoutCurrencyCode": "USD",
      "basePayoutPrice": 822,
      "convenienceFee": 0,
      "currencyCode": "SEK",
      "discount": 5280,
      "discountPrice": 10720,
      "originalPrice": 16000,
      "originalUnitPrice": null,
      "unitPrice": null,
      "vat": 2144,
      "voucherDiscount": 0
    }
  }
}