{
  "id": "b47c17d9c35b43919e3f779a3ae88e94",
  "price": {
    "totalPaymentPrice": {
      "paymentCurrencyAmount": 6955,
      "paymentCurrencyCode": "SEK",
      "paymentCurrencyExchangeRate": 1,
      "paymentCurrencySymbol": "kr"
    },
    "totalPrice": {
      "basePayoutCurrencyCode": "USD",
      "basePayoutPrice": 524,
      "convenienceFee": 0,
      "currencyCode": "SEK",
      "discount": 6955,
      "discountPrice": 6955,
      "originalPrice": 13910,
      "originalUnitPrice": null,
      "unitPrice": null,
      "vat": 1391,
      "voucherDiscount": 0
    }
  }
}