{
  "id": "d176b053d01d4f9b93278f8813e6dfb1",
  "price": {
    "totalPaymentPrice": {
      "paymentCurrencyAmount": 7000,
      "paymentCurrencyCode": "SEK",
      "paymentCurrencyExchangeRate": 1,
      "paymentCurrencySymbol": "kr"
    },
    "totalPrice": {
      "basePayoutCurrencyCode": "USD",
      "basePayoutPrice": 520,
      "convenienceFee": 0,
      "currencyCode": "SEK",
      "discount": 0,
      "discountPrice": 7000,
      "originalPrice": 7000,
      "originalUnitPrice": null,
      "unitPrice": null,
      "vat": 1400,
      "voucherDiscount": 0
    }
  }
}