{
  "id": "d1fbadceb2f741cca1345751df773b5e",
  "price": {
    "totalPaymentPrice": {
      "paymentCurrencyAmount": 13900,
      "paymentCurrencyCode": "SEK",
      "paymentCurrencyExchangeRate": 1,
      "paymentCurrencySymbol": "kr"
    },
    "totalPrice": {
      "basePayoutCurrencyCode": "USD",
      "basePayoutPrice": 1086,
      "convenienceFee": 0,
      "currencyCode": "SEK",
      "discount": 0,
      "discountPrice": 13900,
      "originalPrice": 13900,
      "originalUnitPrice": null,
      "unitPrice": null,
      "vat": 2780,
      "voucherDiscount": 0
    }
  }
}