{
  "id": "565d807f6a2849569656903d10991332",
  "price": {
    "totalPaymentPrice": {
      "paymentCurrencyAmount": 1253,
      "paymentCurrencyCode": "CAD",
      "paymentCurrencyExchangeRate": 1,
      "paymentCurrencySymbol": "$"
    },
    "totalPrice": {
      "basePayoutCurrencyCode": "USD",
      "basePayoutPrice": 914,
      "convenienceFee": 0,
      "currencyCode": "CAD",
      "discount": 1026,
      "discountPrice": 1253,
      "originalPrice": 2279,
      "originalUnitPrice": null,
      "unitPrice": null,
      "vat": 0,
      "voucherDiscount": 0
    }
  }
}