{
  "id": "38ddbc8ca5c446d8be95ccfb8c0f9618",
  "price": {
    "totalPaymentPrice": {
      "paymentCurrencyAmount": 410,
      "paymentCurrencyCode": "JPY",
      "paymentCurrencyExchangeRate": 1,
      "paymentCurrencySymbol": "¥"
    },
    "totalPrice": {
      "basePayoutCurrencyCode": "USD",
      "basePayoutPrice": 268,
      "convenienceFee": 0,
      "currencyCode": "JPY",
      "discount": 0,
      "discountPrice": 410,
      "originalPrice": 410,
      "originalUnitPrice": null,
      "unitPrice": null,
      "vat": 37,
      "voucherDiscount": 0
    }
  }
}