{
  "id": "84ce9926a2d04c06b9b8e99ae09d964c",
  "price": {
    "totalPaymentPrice": {
      "paymentCurrencyAmount": 672,
      "paymentCurrencyCode": "JPY",
      "paymentCurrencyExchangeRate": 1,
      "paymentCurrencySymbol": "¥"
    },
    "totalPrice": {
      "basePayoutCurrencyCode": "USD",
      "basePayoutPrice": 444,
      "convenienceFee": 0,
      "currencyCode": "JPY",
      "discount": 4928,
      "discountPrice": 672,
      "originalPrice": 5600,
      "originalUnitPrice": null,
      "unitPrice": null,
      "vat": 61,
      "voucherDiscount": 0
    }
  }
}