{
  "id": "be0192d357b141b9b16cad35373b1dbb",
  "price": {
    "totalPaymentPrice": {
      "paymentCurrencyAmount": 505,
      "paymentCurrencyCode": "JPY",
      "paymentCurrencyExchangeRate": 1,
      "paymentCurrencySymbol": "¥"
    },
    "totalPrice": {
      "basePayoutCurrencyCode": "USD",
      "basePayoutPrice": 328,
      "convenienceFee": 0,
      "currencyCode": "JPY",
      "discount": 505,
      "discountPrice": 505,
      "originalPrice": 1010,
      "originalUnitPrice": null,
      "unitPrice": null,
      "vat": 46,
      "voucherDiscount": 0
    }
  }
}