{
  "id": "1aa02aa2fcf741a1a7cabb741b269bad",
  "price": {
    "totalPaymentPrice": {
      "paymentCurrencyAmount": 5900,
      "paymentCurrencyCode": "KRW",
      "paymentCurrencyExchangeRate": 1,
      "paymentCurrencySymbol": "₩"
    },
    "totalPrice": {
      "basePayoutCurrencyCode": "USD",
      "basePayoutPrice": 397,
      "convenienceFee": 0,
      "currencyCode": "KRW",
      "discount": 5900,
      "discountPrice": 5900,
      "originalPrice": 11800,
      "originalUnitPrice": null,
      "unitPrice": null,
      "vat": 536,
      "voucherDiscount": 0
    }
  }
}