{
  "id": "5d921696022d4bbe850c76be8c9bc98f",
  "price": {
    "totalPaymentPrice": {
      "paymentCurrencyAmount": 6460,
      "paymentCurrencyCode": "KRW",
      "paymentCurrencyExchangeRate": 1,
      "paymentCurrencySymbol": "₩"
    },
    "totalPrice": {
      "basePayoutCurrencyCode": "USD",
      "basePayoutPrice": 437,
      "convenienceFee": 0,
      "currencyCode": "KRW",
      "discount": 12540,
      "discountPrice": 6460,
      "originalPrice": 19000,
      "originalUnitPrice": null,
      "unitPrice": null,
      "vat": 587,
      "voucherDiscount": 0
    }
  }
}