{
  "id": "da39451c7d094b95b1a34f9fc8428d3e",
  "price": {
    "totalPaymentPrice": {
      "paymentCurrencyAmount": 2750,
      "paymentCurrencyCode": "KRW",
      "paymentCurrencyExchangeRate": 1,
      "paymentCurrencySymbol": "₩"
    },
    "totalPrice": {
      "basePayoutCurrencyCode": "USD",
      "basePayoutPrice": 193,
      "convenienceFee": 0,
      "currencyCode": "KRW",
      "discount": 2750,
      "discountPrice": 2750,
      "originalPrice": 5500,
      "originalUnitPrice": null,
      "unitPrice": null,
      "vat": 250,
      "voucherDiscount": 0
    }
  }
}