{
  "id": "f6e838ff7e1f4a3eb188ba4ddf044dce",
  "price": {
    "totalPaymentPrice": {
      "paymentCurrencyAmount": 1000,
      "paymentCurrencyCode": "KRW",
      "paymentCurrencyExchangeRate": 1,
      "paymentCurrencySymbol": "₩"
    },
    "totalPrice": {
      "basePayoutCurrencyCode": "USD",
      "basePayoutPrice": 71,
      "convenienceFee": 0,
      "currencyCode": "KRW",
      "discount": 0,
      "discountPrice": 1000,
      "originalPrice": 1000,
      "originalUnitPrice": null,
      "unitPrice": null,
      "vat": 91,
      "voucherDiscount": 0
    }
  }
}